[{"CITY":"B","TOWN":"29","SECTION":[{"UNIT":"BG","NAME":"南勢段","SEC":"6100","COMMENT":null},{"UNIT":"BG","NAME":"博愛段","SEC":"6101","COMMENT":null},{"UNIT":"BG","NAME":"谷關段","SEC":"6102","COMMENT":null},{"UNIT":"BG","NAME":"達見段","SEC":"6103","COMMENT":null},{"UNIT":"BG","NAME":"青山段","SEC":"6104","COMMENT":"註銷"},{"UNIT":"BG","NAME":"佳陽段","SEC":"6105","COMMENT":null},{"UNIT":"BG","NAME":"梨山段","SEC":"6106","COMMENT":null},{"UNIT":"BG","NAME":"松茂段","SEC":"6107","COMMENT":null},{"UNIT":"BG","NAME":"環山段","SEC":"6108","COMMENT":null},{"UNIT":"BG","NAME":"志良段","SEC":"6109","COMMENT":null},{"UNIT":"BG","NAME":"勝光段","SEC":"6110","COMMENT":null},{"UNIT":"BG","NAME":"七家灣段","SEC":"6111","COMMENT":null},{"UNIT":"BG","NAME":"思源段","SEC":"6112","COMMENT":null},{"UNIT":"BG","NAME":"武陵段","SEC":"6113","COMMENT":null},{"UNIT":"BG","NAME":"福壽山段","SEC":"6114","COMMENT":null},{"UNIT":"BG","NAME":"雙崎段","SEC":"6115","COMMENT":null},{"UNIT":"BG","NAME":"白毛段","SEC":"6116","COMMENT":null},{"UNIT":"BG","NAME":"達觀段","SEC":"6117","COMMENT":null},{"UNIT":"BG","NAME":"雪山段","SEC":"6118","COMMENT":null},{"UNIT":"BG","NAME":"埋伏坪社段","SEC":"6119","COMMENT":null},{"UNIT":"BG","NAME":"黑田段","SEC":"6120","COMMENT":null},{"UNIT":"BG","NAME":"七卡段","SEC":"6121","COMMENT":null},{"UNIT":"BG","NAME":"桃山段","SEC":"6122","COMMENT":null},{"UNIT":"BG","NAME":"松嶺段","SEC":"6123","COMMENT":null},{"UNIT":"BG","NAME":"松盧段","SEC":"6124","COMMENT":null},{"UNIT":"BG","NAME":"龍谷段","SEC":"6125","COMMENT":null},{"UNIT":"BG","NAME":"小雪山段","SEC":"6126","COMMENT":null},{"UNIT":"BG","NAME":"鞍馬山段","SEC":"6127","COMMENT":null},{"UNIT":"BG","NAME":"新山段","SEC":"6128","COMMENT":null},{"UNIT":"BG","NAME":"佳保段","SEC":"6129","COMMENT":null},{"UNIT":"BG","NAME":"自由段","SEC":"6130","COMMENT":null},{"UNIT":"BG","NAME":"後山寮段","SEC":"6131","COMMENT":null},{"UNIT":"BG","NAME":"苗圃段","SEC":"6132","COMMENT":"更正"},{"UNIT":"BG","NAME":"阿冷段","SEC":"6133","COMMENT":null},{"UNIT":"BG","NAME":"光明段","SEC":"6134","COMMENT":null},{"UNIT":"BG","NAME":"劍山段","SEC":"6135","COMMENT":null},{"UNIT":"BG","NAME":"釜碗段","SEC":"6136","COMMENT":null},{"UNIT":"BG","NAME":"壩新段","SEC":"6137","COMMENT":null},{"UNIT":"BG","NAME":"三錐段","SEC":"6138","COMMENT":null},{"UNIT":"BG","NAME":"大雪山段","SEC":"6139","COMMENT":null},{"UNIT":"BG","NAME":"裡冷段","SEC":"6140","COMMENT":null},{"UNIT":"BG","NAME":"沙蓮溪段","SEC":"6141","COMMENT":null},{"UNIT":"BG","NAME":"天輪段","SEC":"6142","COMMENT":null},{"UNIT":"BG","NAME":"東卯段","SEC":"6143","COMMENT":null},{"UNIT":"BG","NAME":"鞍馬溪段","SEC":"6144","COMMENT":null},{"UNIT":"BG","NAME":"火石段","SEC":"6145","COMMENT":null},{"UNIT":"BG","NAME":"唐呂段","SEC":"6146","COMMENT":"更正"},{"UNIT":"BG","NAME":"十文溪段","SEC":"6147","COMMENT":null},{"UNIT":"BG","NAME":"西川段","SEC":"6148","COMMENT":null},{"UNIT":"BG","NAME":"天池段","SEC":"6149","COMMENT":null},{"UNIT":"BG","NAME":"七棟寮段","SEC":"6150","COMMENT":null},{"UNIT":"BG","NAME":"百川段","SEC":"6151","COMMENT":null},{"UNIT":"BG","NAME":"出雲山段","SEC":"6152","COMMENT":null},{"UNIT":"BG","NAME":"達盤段","SEC":"6153","COMMENT":null},{"UNIT":"BG","NAME":"大木段","SEC":"6154","COMMENT":null},{"UNIT":"BG","NAME":"仁壽段","SEC":"6155","COMMENT":null},{"UNIT":"BG","NAME":"興隆段","SEC":"6156","COMMENT":null},{"UNIT":"BG","NAME":"四季段","SEC":"6157","COMMENT":null},{"UNIT":"BG","NAME":"池有段","SEC":"6158","COMMENT":null},{"UNIT":"BG","NAME":"羅葉尾段","SEC":"6159","COMMENT":null},{"UNIT":"BG","NAME":"有勝段","SEC":"6160","COMMENT":null},{"UNIT":"BG","NAME":"南湖段","SEC":"6161","COMMENT":null},{"UNIT":"BG","NAME":"中央段","SEC":"6162","COMMENT":null},{"UNIT":"BG","NAME":"羅閑段","SEC":"6163","COMMENT":null},{"UNIT":"BG","NAME":"無明段","SEC":"6164","COMMENT":null},{"UNIT":"BG","NAME":"捫山段","SEC":"6165","COMMENT":null},{"UNIT":"BG","NAME":"育苗段","SEC":"6166","COMMENT":null},{"UNIT":"BG","NAME":"崑崙段","SEC":"6167","COMMENT":null},{"UNIT":"BG","NAME":"中坑段","SEC":"6168","COMMENT":null},{"UNIT":"BG","NAME":"橫流溪段","SEC":"6169","COMMENT":null},{"UNIT":"BG","NAME":"東卯溪段","SEC":"6170","COMMENT":null},{"UNIT":"BG","NAME":"稍來段","SEC":"6171","COMMENT":null},{"UNIT":"BG","NAME":"白鹿段","SEC":"6172","COMMENT":null},{"UNIT":"BG","NAME":"裡冷溪段","SEC":"6173","COMMENT":null},{"UNIT":"BG","NAME":"八仙山段","SEC":"6174","COMMENT":null},{"UNIT":"BG","NAME":"雪山坑段","SEC":"6175","COMMENT":null},{"UNIT":"BG","NAME":"摩天嶺段","SEC":"6176","COMMENT":null},{"UNIT":"BG","NAME":"烏石坑段","SEC":"6177","COMMENT":null},{"UNIT":"BG","NAME":"觀音溪段","SEC":"6178","COMMENT":null},{"UNIT":"BG","NAME":"合歡溪段","SEC":"6179","COMMENT":null},{"UNIT":"BG","NAME":"白毛山段","SEC":"6180","COMMENT":null},{"UNIT":"BG","NAME":"長興段","SEC":"6181","COMMENT":null}]}]