[{"CITY":"D","TOWN":"02","SECTION":[{"UNIT":"DC","NAME":"桶盤淺段","SEC":"1801","COMMENT":"調整"},{"UNIT":"DC","NAME":"公英段","SEC":"1802","COMMENT":"調整"},{"UNIT":"DC","NAME":"鹽埕段","SEC":"1803","COMMENT":null},{"UNIT":"DC","NAME":"灣裡段","SEC":"1804","COMMENT":"註銷"},{"UNIT":"DC","NAME":"下鯤鯓段","SEC":"1805","COMMENT":"註銷"},{"UNIT":"DC","NAME":"鞍子段","SEC":"1806","COMMENT":"註銷"},{"UNIT":"DC","NAME":"新興段","SEC":"1808","COMMENT":null},{"UNIT":"DC","NAME":"喜東段","SEC":"1809","COMMENT":null},{"UNIT":"DC","NAME":"喜北段","SEC":"1810","COMMENT":null},{"UNIT":"DC","NAME":"省躬段","SEC":"1811","COMMENT":null},{"UNIT":"DC","NAME":"中和段","SEC":"1812","COMMENT":null},{"UNIT":"DC","NAME":"南山段","SEC":"1813","COMMENT":null},{"UNIT":"DC","NAME":"福吉段","SEC":"1814","COMMENT":null},{"UNIT":"DC","NAME":"大林段","SEC":"1851","COMMENT":null},{"UNIT":"DC","NAME":"大忠段","SEC":"1852","COMMENT":null},{"UNIT":"DC","NAME":"大恩段","SEC":"1853","COMMENT":null},{"UNIT":"DC","NAME":"新都段","SEC":"1854","COMMENT":null},{"UNIT":"DC","NAME":"建南段","SEC":"1855","COMMENT":null},{"UNIT":"DC","NAME":"南鞍段","SEC":"1856","COMMENT":null},{"UNIT":"DC","NAME":"永寧段","SEC":"1857","COMMENT":null},{"UNIT":"DC","NAME":"興農段","SEC":"1858","COMMENT":null},{"UNIT":"DC","NAME":"舉喜段","SEC":"1859","COMMENT":null},{"UNIT":"DC","NAME":"同安段","SEC":"1860","COMMENT":null},{"UNIT":"DC","NAME":"龍崗段","SEC":"1861","COMMENT":null},{"UNIT":"DC","NAME":"華南段","SEC":"1862","COMMENT":null},{"UNIT":"DC","NAME":"南豐段","SEC":"1863","COMMENT":null},{"UNIT":"DC","NAME":"明興段","SEC":"1864","COMMENT":null},{"UNIT":"DC","NAME":"正義段","SEC":"1865","COMMENT":null},{"UNIT":"DC","NAME":"水交社段","SEC":"1866","COMMENT":null},{"UNIT":"DC","NAME":"日新段","SEC":"1867","COMMENT":null},{"UNIT":"DC","NAME":"天后段","SEC":"1868","COMMENT":null},{"UNIT":"DC","NAME":"白雪段","SEC":"1869","COMMENT":null},{"UNIT":"DC","NAME":"南華段","SEC":"1870","COMMENT":null},{"UNIT":"DC","NAME":"大山段","SEC":"1871","COMMENT":"增編"}]}]