[{"CITY":"D","TOWN":"27","SECTION":[{"UNIT":"DH","NAME":"善化段","SEC":"6713","COMMENT":null},{"UNIT":"DH","NAME":"曾文段","SEC":"6714","COMMENT":null},{"UNIT":"DH","NAME":"東勢寮段","SEC":"6715","COMMENT":null},{"UNIT":"DH","NAME":"東勢寮段一小段","SEC":"6716","COMMENT":null},{"UNIT":"DH","NAME":"東勢寮段二小段","SEC":"6717","COMMENT":null},{"UNIT":"DH","NAME":"北子店段","SEC":"6718","COMMENT":null},{"UNIT":"DH","NAME":"北子店段一小段","SEC":"6719","COMMENT":null},{"UNIT":"DH","NAME":"北子店段二小段","SEC":"6720","COMMENT":null},{"UNIT":"DH","NAME":"茄拔段","SEC":"6721","COMMENT":null},{"UNIT":"DH","NAME":"茄拔段一小段","SEC":"6722","COMMENT":null},{"UNIT":"DH","NAME":"茄拔段二小段","SEC":"6723","COMMENT":null},{"UNIT":"DH","NAME":"小新營段","SEC":"6724","COMMENT":null},{"UNIT":"DH","NAME":"坐駕段","SEC":"6725","COMMENT":null},{"UNIT":"DH","NAME":"六分寮段","SEC":"6726","COMMENT":null},{"UNIT":"DH","NAME":"胡厝寮段","SEC":"6727","COMMENT":null},{"UNIT":"DH","NAME":"善成段","SEC":"6763","COMMENT":null},{"UNIT":"DH","NAME":"善駕段","SEC":"6764","COMMENT":null},{"UNIT":"DH","NAME":"善中段","SEC":"6765","COMMENT":null},{"UNIT":"DH","NAME":"善文段","SEC":"6766","COMMENT":null},{"UNIT":"DH","NAME":"善昌段","SEC":"6767","COMMENT":null},{"UNIT":"DH","NAME":"善南段","SEC":"6768","COMMENT":null},{"UNIT":"DH","NAME":"善西段","SEC":"6769","COMMENT":null},{"UNIT":"DH","NAME":"善進段","SEC":"6790","COMMENT":null},{"UNIT":"DH","NAME":"善科段","SEC":"6796","COMMENT":null},{"UNIT":"DH","NAME":"善晶段","SEC":"6800","COMMENT":null},{"UNIT":"DH","NAME":"善新段","SEC":"6802","COMMENT":null},{"UNIT":"DH","NAME":"慶安段","SEC":"6816","COMMENT":null},{"UNIT":"DH","NAME":"文正段","SEC":"6817","COMMENT":null},{"UNIT":"DH","NAME":"光華段","SEC":"6818","COMMENT":null},{"UNIT":"DH","NAME":"光文段","SEC":"6819","COMMENT":null},{"UNIT":"DH","NAME":"大成段","SEC":"6820","COMMENT":null},{"UNIT":"DH","NAME":"圳西段","SEC":"6821","COMMENT":null},{"UNIT":"DH","NAME":"德興段","SEC":"6823","COMMENT":null},{"UNIT":"DH","NAME":"大同段","SEC":"6824","COMMENT":null},{"UNIT":"DH","NAME":"灣裡段","SEC":"6825","COMMENT":null},{"UNIT":"DH","NAME":"成功段","SEC":"6826","COMMENT":null},{"UNIT":"DH","NAME":"什美段","SEC":"6827","COMMENT":null},{"UNIT":"DH","NAME":"北小新段","SEC":"6828","COMMENT":null},{"UNIT":"DH","NAME":"南小新段","SEC":"6829","COMMENT":"增編"},{"UNIT":"DH","NAME":"胡厝段","SEC":"6830","COMMENT":"增編"}]}]