[{"CITY":"E","TOWN":"26","SECTION":[{"UNIT":"EJ","NAME":"砂崙段","SEC":"3000","COMMENT":"註銷"},{"UNIT":"EJ","NAME":"頂茄萣段","SEC":"3001","COMMENT":null},{"UNIT":"EJ","NAME":"頂茄萣段一小段","SEC":"3002","COMMENT":null},{"UNIT":"EJ","NAME":"頂茄萣段二小段","SEC":"3003","COMMENT":null},{"UNIT":"EJ","NAME":"崎漏段","SEC":"3004","COMMENT":null},{"UNIT":"EJ","NAME":"崎漏段一小段","SEC":"3005","COMMENT":null},{"UNIT":"EJ","NAME":"白雲段","SEC":"3006","COMMENT":null},{"UNIT":"EJ","NAME":"福東段","SEC":"3007","COMMENT":null},{"UNIT":"EJ","NAME":"福西段","SEC":"3008","COMMENT":null},{"UNIT":"EJ","NAME":"白砂段","SEC":"3009","COMMENT":null},{"UNIT":"EJ","NAME":"賜福段","SEC":"3010","COMMENT":null},{"UNIT":"EJ","NAME":"保萣段","SEC":"3011","COMMENT":null},{"UNIT":"EJ","NAME":"嘉萣段","SEC":"3012","COMMENT":null},{"UNIT":"EJ","NAME":"雙萣段","SEC":"3013","COMMENT":null},{"UNIT":"EJ","NAME":"成功段","SEC":"3014","COMMENT":null},{"UNIT":"EJ","NAME":"正順段","SEC":"3015","COMMENT":null},{"UNIT":"EJ","NAME":"興達段","SEC":"3016","COMMENT":"增編"}]}]