[{"CITY":"P","TOWN":"17","SECTION":[{"UNIT":"PE","NAME":"元長段","SEC":"0610","COMMENT":null},{"UNIT":"PE","NAME":"長南段","SEC":"0611","COMMENT":null},{"UNIT":"PE","NAME":"客子厝段","SEC":"0612","COMMENT":null},{"UNIT":"PE","NAME":"下寮段","SEC":"0613","COMMENT":null},{"UNIT":"PE","NAME":"頂寮段","SEC":"0614","COMMENT":null},{"UNIT":"PE","NAME":"內寮段","SEC":"0615","COMMENT":null},{"UNIT":"PE","NAME":"子茂段","SEC":"0616","COMMENT":null},{"UNIT":"PE","NAME":"龍岩厝段","SEC":"0617","COMMENT":null},{"UNIT":"PE","NAME":"合和段","SEC":"0618","COMMENT":null},{"UNIT":"PE","NAME":"山子內段","SEC":"0619","COMMENT":null},{"UNIT":"PE","NAME":"鹿寮段","SEC":"0620","COMMENT":null},{"UNIT":"PE","NAME":"後湖段","SEC":"0621","COMMENT":null},{"UNIT":"PE","NAME":"五塊寮段","SEC":"0622","COMMENT":null},{"UNIT":"PE","NAME":"潭內段","SEC":"0623","COMMENT":null},{"UNIT":"PE","NAME":"興茂段","SEC":"0624","COMMENT":null},{"UNIT":"PE","NAME":"中坑段","SEC":"0625","COMMENT":null},{"UNIT":"PE","NAME":"長北段","SEC":"0626","COMMENT":null},{"UNIT":"PE","NAME":"中湖段","SEC":"0627","COMMENT":null},{"UNIT":"PE","NAME":"長興段","SEC":"0628","COMMENT":null},{"UNIT":"PE","NAME":"仁德段","SEC":"0680","COMMENT":null},{"UNIT":"PE","NAME":"東庄段","SEC":"0681","COMMENT":null},{"UNIT":"PE","NAME":"瓦段","SEC":"0682","COMMENT":null},{"UNIT":"PE","NAME":"部子段","SEC":"0683","COMMENT":null},{"UNIT":"PE","NAME":"崙子段","SEC":"0684","COMMENT":null},{"UNIT":"PE","NAME":"潭墘段","SEC":"0685","COMMENT":null},{"UNIT":"PE","NAME":"三和段","SEC":"0702","COMMENT":null},{"UNIT":"PE","NAME":"山茂段","SEC":"0703","COMMENT":null},{"UNIT":"PE","NAME":"青山段","SEC":"0704","COMMENT":null},{"UNIT":"PE","NAME":"和平段","SEC":"0709","COMMENT":"註銷"},{"UNIT":"PE","NAME":"信義段","SEC":"0710","COMMENT":null},{"UNIT":"PE","NAME":"新吉段","SEC":"0714","COMMENT":null},{"UNIT":"PE","NAME":"鹿南段","SEC":"0748","COMMENT":null},{"UNIT":"PE","NAME":"鹿北段","SEC":"0749","COMMENT":null},{"UNIT":"PE","NAME":"義天段","SEC":"0750","COMMENT":null},{"UNIT":"PE","NAME":"極明段","SEC":"0751","COMMENT":null},{"UNIT":"PE","NAME":"西湖段","SEC":"0754","COMMENT":null},{"UNIT":"PE","NAME":"東湖段","SEC":"0755","COMMENT":"更正"},{"UNIT":"PE","NAME":"北湖段","SEC":"0756","COMMENT":"更正"}]}]