[{"CITY":"T","TOWN":"12","SECTION":[{"UNIT":"TC","NAME":"萬巒段","SEC":"0308","COMMENT":null},{"UNIT":"TC","NAME":"四溝水段","SEC":"0309","COMMENT":null},{"UNIT":"TC","NAME":"五溝水段","SEC":"0310","COMMENT":null},{"UNIT":"TC","NAME":"赤山段","SEC":"0311","COMMENT":null},{"UNIT":"TC","NAME":"赤山段一小段","SEC":"0312","COMMENT":null},{"UNIT":"TC","NAME":"新厝段","SEC":"0313","COMMENT":null},{"UNIT":"TC","NAME":"新厝段一小段","SEC":"0314","COMMENT":null},{"UNIT":"TC","NAME":"佳佐段","SEC":"0315","COMMENT":null},{"UNIT":"TC","NAME":"佳佐段一小段","SEC":"0316","COMMENT":null},{"UNIT":"TC","NAME":"新置段","SEC":"0472","COMMENT":null},{"UNIT":"TC","NAME":"萬全段","SEC":"0476","COMMENT":null},{"UNIT":"TC","NAME":"官倉段","SEC":"0477","COMMENT":null},{"UNIT":"TC","NAME":"萬和段","SEC":"0478","COMMENT":null},{"UNIT":"TC","NAME":"民生段","SEC":"1519","COMMENT":null},{"UNIT":"TC","NAME":"佳和段","SEC":"1520","COMMENT":null},{"UNIT":"TC","NAME":"頭溝水段","SEC":"1521","COMMENT":null},{"UNIT":"TC","NAME":"鹿寮段","SEC":"1522","COMMENT":null},{"UNIT":"TC","NAME":"見月段","SEC":"1523","COMMENT":null},{"UNIT":"TC","NAME":"新和段","SEC":"1524","COMMENT":null},{"UNIT":"TC","NAME":"永慶段","SEC":"1529","COMMENT":null},{"UNIT":"TC","NAME":"西盛段","SEC":"1530","COMMENT":null},{"UNIT":"TC","NAME":"大林段","SEC":"1531","COMMENT":null},{"UNIT":"TC","NAME":"德勝段","SEC":"1532","COMMENT":null},{"UNIT":"TC","NAME":"新庄段","SEC":"1533","COMMENT":null},{"UNIT":"TC","NAME":"柑園段","SEC":"1534","COMMENT":null},{"UNIT":"TC","NAME":"成德段","SEC":"1535","COMMENT":null},{"UNIT":"TC","NAME":"三民段","SEC":"1536","COMMENT":null},{"UNIT":"TC","NAME":"牛角灣段","SEC":"1537","COMMENT":null},{"UNIT":"TC","NAME":"萬金段","SEC":"1538","COMMENT":null},{"UNIT":"TC","NAME":"赤新段","SEC":"1539","COMMENT":null},{"UNIT":"TC","NAME":"富山段","SEC":"1540","COMMENT":null},{"UNIT":"TC","NAME":"新農段","SEC":"1541","COMMENT":"更正"}]}]