[{"CITY":"X","TOWN":"04","SECTION":[{"UNIT":"XA","NAME":"小池角段","SEC":"0063","COMMENT":"註銷"},{"UNIT":"XA","NAME":"二崁段","SEC":"0064","COMMENT":null},{"UNIT":"XA","NAME":"合界頭段","SEC":"0065","COMMENT":null},{"UNIT":"XA","NAME":"竹篙灣段","SEC":"0066","COMMENT":null},{"UNIT":"XA","NAME":"大池角段","SEC":"0067","COMMENT":null},{"UNIT":"XA","NAME":"內垵段","SEC":"0068","COMMENT":"註銷"},{"UNIT":"XA","NAME":"緝馬灣段","SEC":"0069","COMMENT":null},{"UNIT":"XA","NAME":"橫礁段","SEC":"0070","COMMENT":null},{"UNIT":"XA","NAME":"外垵段","SEC":"0071","COMMENT":"註銷"},{"UNIT":"XA","NAME":"外垵一段","SEC":"0151","COMMENT":null},{"UNIT":"XA","NAME":"外垵二段","SEC":"0152","COMMENT":null},{"UNIT":"XA","NAME":"二崁南段","SEC":"0153","COMMENT":null},{"UNIT":"XA","NAME":"二崁北段","SEC":"0154","COMMENT":null},{"UNIT":"XA","NAME":"外垵三段","SEC":"0155","COMMENT":null},{"UNIT":"XA","NAME":"內垵一段","SEC":"0156","COMMENT":null},{"UNIT":"XA","NAME":"內垵二段","SEC":"0157","COMMENT":null},{"UNIT":"XA","NAME":"內垵三段","SEC":"0158","COMMENT":null},{"UNIT":"XA","NAME":"赤馬一段","SEC":"0159","COMMENT":null},{"UNIT":"XA","NAME":"海墘嶼段","SEC":"0200","COMMENT":null},{"UNIT":"XA","NAME":"合界段","SEC":"0268","COMMENT":null},{"UNIT":"XA","NAME":"竹灣段","SEC":"0269","COMMENT":null},{"UNIT":"XA","NAME":"小門段","SEC":"0270","COMMENT":null},{"UNIT":"XA","NAME":"大池段","SEC":"0271","COMMENT":null},{"UNIT":"XA","NAME":"池西段","SEC":"0272","COMMENT":null},{"UNIT":"XA","NAME":"池東段","SEC":"0273","COMMENT":null},{"UNIT":"XA","NAME":"赤馬二段","SEC":"0274","COMMENT":null},{"UNIT":"XA","NAME":"橫礁新段","SEC":"0275","COMMENT":null}]}]